[
  {
    "project": {
      "dir_name": "baberrehman-@@-interactive-theorem-proving",
      "split": {
        "dir_name": "train-rl-repos",
        "thm_dir_name": "train-rl-theorems"
      },
      "commit_hash": null,
      "compile_args": []
    },
    "path": "coq-art-8.13.0/ch8_inductive_predicates/SRC/last.v",
    "theorem_start_pos": {
      "line": 20,
      "column": 2
    },
    "theorem_end_pos": {
      "line": 21,
      "column": 61
    },
    "proof_start_pos": {
      "line": 22,
      "column": 2
    },
    "proof_end_pos": {
      "line": 28,
      "column": 6
    },
    "hash": "4d7463cb589e1151861e44564fc5c71537551aa9ab2f784ab89a28794ab32e53"
  },
  {
    "project": {
      "dir_name": "baberrehman-@@-interactive-theorem-proving",
      "split": {
        "dir_name": "train-rl-repos",
        "thm_dir_name": "train-rl-theorems"
      },
      "commit_hash": null,
      "compile_args": []
    },
    "path": "coq-art-8.13.0/ch8_inductive_predicates/SRC/last.v",
    "theorem_start_pos": {
      "line": 30,
      "column": 2
    },
    "theorem_end_pos": {
      "line": 31,
      "column": 61
    },
    "proof_start_pos": {
      "line": 32,
      "column": 2
    },
    "proof_end_pos": {
      "line": 38,
      "column": 6
    },
    "hash": "4d7463cb589e1151861e44564fc5c71537551aa9ab2f784ab89a28794ab32e53"
  },
  {
    "project": {
      "dir_name": "baberrehman-@@-interactive-theorem-proving",
      "split": {
        "dir_name": "train-rl-repos",
        "thm_dir_name": "train-rl-theorems"
      },
      "commit_hash": null,
      "compile_args": []
    },
    "path": "coq-art-8.13.0/ch8_inductive_predicates/SRC/last.v",
    "theorem_start_pos": {
      "line": 40,
      "column": 2
    },
    "theorem_end_pos": {
      "line": 40,
      "column": 78
    },
    "proof_start_pos": {
      "line": 41,
      "column": 2
    },
    "proof_end_pos": {
      "line": 46,
      "column": 6
    },
    "hash": "4d7463cb589e1151861e44564fc5c71537551aa9ab2f784ab89a28794ab32e53"
  },
  {
    "project": {
      "dir_name": "baberrehman-@@-interactive-theorem-proving",
      "split": {
        "dir_name": "train-rl-repos",
        "thm_dir_name": "train-rl-theorems"
      },
      "commit_hash": null,
      "compile_args": []
    },
    "path": "coq-art-8.13.0/ch8_inductive_predicates/SRC/last.v",
    "theorem_start_pos": {
      "line": 48,
      "column": 2
    },
    "theorem_end_pos": {
      "line": 49,
      "column": 65
    },
    "proof_start_pos": {
      "line": 50,
      "column": 2
    },
    "proof_end_pos": {
      "line": 54,
      "column": 6
    },
    "hash": "4d7463cb589e1151861e44564fc5c71537551aa9ab2f784ab89a28794ab32e53"
  }
]