[
  {
    "project": {
      "dir_name": "mattam82-@@-Coq-misc",
      "split": {
        "dir_name": "train-sft-repos",
        "thm_dir_name": "train-sft-theorems"
      },
      "commit_hash": null,
      "compile_args": []
    },
    "path": "theories/Lists/ListSet.v",
    "theorem_start_pos": {
      "line": 84,
      "column": 2
    },
    "theorem_end_pos": {
      "line": 84,
      "column": 73
    },
    "proof_start_pos": {
      "line": 86,
      "column": 2
    },
    "proof_end_pos": {
      "line": 97,
      "column": 6
    },
    "hash": "d3652997a88a64144b2e0c72a65256424250e335d651949ccae667b8d6dd023c"
  },
  {
    "project": {
      "dir_name": "mattam82-@@-Coq-misc",
      "split": {
        "dir_name": "train-sft-repos",
        "thm_dir_name": "train-sft-theorems"
      },
      "commit_hash": null,
      "compile_args": []
    },
    "path": "theories/Lists/ListSet.v",
    "theorem_start_pos": {
      "line": 99,
      "column": 2
    },
    "theorem_end_pos": {
      "line": 101,
      "column": 68
    },
    "proof_start_pos": {
      "line": 103,
      "column": 2
    },
    "proof_end_pos": {
      "line": 107,
      "column": 6
    },
    "hash": "d3652997a88a64144b2e0c72a65256424250e335d651949ccae667b8d6dd023c"
  },
  {
    "project": {
      "dir_name": "mattam82-@@-Coq-misc",
      "split": {
        "dir_name": "train-sft-repos",
        "thm_dir_name": "train-sft-theorems"
      },
      "commit_hash": null,
      "compile_args": []
    },
    "path": "theories/Lists/ListSet.v",
    "theorem_start_pos": {
      "line": 109,
      "column": 2
    },
    "theorem_end_pos": {
      "line": 112,
      "column": 63
    },
    "proof_start_pos": {
      "line": 114,
      "column": 2
    },
    "proof_end_pos": {
      "line": 121,
      "column": 6
    },
    "hash": "d3652997a88a64144b2e0c72a65256424250e335d651949ccae667b8d6dd023c"
  },
  {
    "project": {
      "dir_name": "mattam82-@@-Coq-misc",
      "split": {
        "dir_name": "train-sft-repos",
        "thm_dir_name": "train-sft-theorems"
      },
      "commit_hash": null,
      "compile_args": []
    },
    "path": "theories/Lists/ListSet.v",
    "theorem_start_pos": {
      "line": 124,
      "column": 2
    },
    "theorem_end_pos": {
      "line": 125,
      "column": 58
    },
    "proof_start_pos": {
      "line": 126,
      "column": 2
    },
    "proof_end_pos": {
      "line": 130,
      "column": 6
    },
    "hash": "d3652997a88a64144b2e0c72a65256424250e335d651949ccae667b8d6dd023c"
  },
  {
    "project": {
      "dir_name": "mattam82-@@-Coq-misc",
      "split": {
        "dir_name": "train-sft-repos",
        "thm_dir_name": "train-sft-theorems"
      },
      "commit_hash": null,
      "compile_args": []
    },
    "path": "theories/Lists/ListSet.v",
    "theorem_start_pos": {
      "line": 132,
      "column": 2
    },
    "theorem_end_pos": {
      "line": 133,
      "column": 58
    },
    "proof_start_pos": {
      "line": 134,
      "column": 2
    },
    "proof_end_pos": {
      "line": 141,
      "column": 6
    },
    "hash": "d3652997a88a64144b2e0c72a65256424250e335d651949ccae667b8d6dd023c"
  },
  {
    "project": {
      "dir_name": "mattam82-@@-Coq-misc",
      "split": {
        "dir_name": "train-sft-repos",
        "thm_dir_name": "train-sft-theorems"
      },
      "commit_hash": null,
      "compile_args": []
    },
    "path": "theories/Lists/ListSet.v",
    "theorem_start_pos": {
      "line": 143,
      "column": 2
    },
    "theorem_end_pos": {
      "line": 144,
      "column": 61
    },
    "proof_start_pos": {
      "line": 145,
      "column": 2
    },
    "proof_end_pos": {
      "line": 151,
      "column": 6
    },
    "hash": "d3652997a88a64144b2e0c72a65256424250e335d651949ccae667b8d6dd023c"
  },
  {
    "project": {
      "dir_name": "mattam82-@@-Coq-misc",
      "split": {
        "dir_name": "train-sft-repos",
        "thm_dir_name": "train-sft-theorems"
      },
      "commit_hash": null,
      "compile_args": []
    },
    "path": "theories/Lists/ListSet.v",
    "theorem_start_pos": {
      "line": 153,
      "column": 2
    },
    "theorem_end_pos": {
      "line": 154,
      "column": 61
    },
    "proof_start_pos": {
      "line": 155,
      "column": 2
    },
    "proof_end_pos": {
      "line": 161,
      "column": 6
    },
    "hash": "d3652997a88a64144b2e0c72a65256424250e335d651949ccae667b8d6dd023c"
  },
  {
    "project": {
      "dir_name": "mattam82-@@-Coq-misc",
      "split": {
        "dir_name": "train-sft-repos",
        "thm_dir_name": "train-sft-theorems"
      },
      "commit_hash": null,
      "compile_args": []
    },
    "path": "theories/Lists/ListSet.v",
    "theorem_start_pos": {
      "line": 163,
      "column": 2
    },
    "theorem_end_pos": {
      "line": 164,
      "column": 64
    },
    "proof_start_pos": {
      "line": 166,
      "column": 2
    },
    "proof_end_pos": {
      "line": 172,
      "column": 6
    },
    "hash": "d3652997a88a64144b2e0c72a65256424250e335d651949ccae667b8d6dd023c"
  },
  {
    "project": {
      "dir_name": "mattam82-@@-Coq-misc",
      "split": {
        "dir_name": "train-sft-repos",
        "thm_dir_name": "train-sft-theorems"
      },
      "commit_hash": null,
      "compile_args": []
    },
    "path": "theories/Lists/ListSet.v",
    "theorem_start_pos": {
      "line": 174,
      "column": 2
    },
    "theorem_end_pos": {
      "line": 175,
      "column": 59
    },
    "proof_start_pos": {
      "line": 177,
      "column": 2
    },
    "proof_end_pos": {
      "line": 185,
      "column": 6
    },
    "hash": "d3652997a88a64144b2e0c72a65256424250e335d651949ccae667b8d6dd023c"
  },
  {
    "project": {
      "dir_name": "mattam82-@@-Coq-misc",
      "split": {
        "dir_name": "train-sft-repos",
        "thm_dir_name": "train-sft-theorems"
      },
      "commit_hash": null,
      "compile_args": []
    },
    "path": "theories/Lists/ListSet.v",
    "theorem_start_pos": {
      "line": 189,
      "column": 2
    },
    "theorem_end_pos": {
      "line": 190,
      "column": 73
    },
    "proof_start_pos": {
      "line": 192,
      "column": 2
    },
    "proof_end_pos": {
      "line": 194,
      "column": 6
    },
    "hash": "d3652997a88a64144b2e0c72a65256424250e335d651949ccae667b8d6dd023c"
  },
  {
    "project": {
      "dir_name": "mattam82-@@-Coq-misc",
      "split": {
        "dir_name": "train-sft-repos",
        "thm_dir_name": "train-sft-theorems"
      },
      "commit_hash": null,
      "compile_args": []
    },
    "path": "theories/Lists/ListSet.v",
    "theorem_start_pos": {
      "line": 196,
      "column": 2
    },
    "theorem_end_pos": {
      "line": 197,
      "column": 73
    },
    "proof_start_pos": {
      "line": 199,
      "column": 2
    },
    "proof_end_pos": {
      "line": 210,
      "column": 6
    },
    "hash": "d3652997a88a64144b2e0c72a65256424250e335d651949ccae667b8d6dd023c"
  },
  {
    "project": {
      "dir_name": "mattam82-@@-Coq-misc",
      "split": {
        "dir_name": "train-sft-repos",
        "thm_dir_name": "train-sft-theorems"
      },
      "commit_hash": null,
      "compile_args": []
    },
    "path": "theories/Lists/ListSet.v",
    "theorem_start_pos": {
      "line": 212,
      "column": 2
    },
    "theorem_end_pos": {
      "line": 213,
      "column": 74
    },
    "proof_start_pos": {
      "line": 214,
      "column": 3
    },
    "proof_end_pos": {
      "line": 216,
      "column": 7
    },
    "hash": "d3652997a88a64144b2e0c72a65256424250e335d651949ccae667b8d6dd023c"
  },
  {
    "project": {
      "dir_name": "mattam82-@@-Coq-misc",
      "split": {
        "dir_name": "train-sft-repos",
        "thm_dir_name": "train-sft-theorems"
      },
      "commit_hash": null,
      "compile_args": []
    },
    "path": "theories/Lists/ListSet.v",
    "theorem_start_pos": {
      "line": 220,
      "column": 2
    },
    "theorem_end_pos": {
      "line": 220,
      "column": 75
    },
    "proof_start_pos": {
      "line": 221,
      "column": 2
    },
    "proof_end_pos": {
      "line": 225,
      "column": 6
    },
    "hash": "d3652997a88a64144b2e0c72a65256424250e335d651949ccae667b8d6dd023c"
  },
  {
    "project": {
      "dir_name": "mattam82-@@-Coq-misc",
      "split": {
        "dir_name": "train-sft-repos",
        "thm_dir_name": "train-sft-theorems"
      },
      "commit_hash": null,
      "compile_args": []
    },
    "path": "theories/Lists/ListSet.v",
    "theorem_start_pos": {
      "line": 228,
      "column": 2
    },
    "theorem_end_pos": {
      "line": 229,
      "column": 66
    },
    "proof_start_pos": {
      "line": 230,
      "column": 2
    },
    "proof_end_pos": {
      "line": 232,
      "column": 6
    },
    "hash": "d3652997a88a64144b2e0c72a65256424250e335d651949ccae667b8d6dd023c"
  },
  {
    "project": {
      "dir_name": "mattam82-@@-Coq-misc",
      "split": {
        "dir_name": "train-sft-repos",
        "thm_dir_name": "train-sft-theorems"
      },
      "commit_hash": null,
      "compile_args": []
    },
    "path": "theories/Lists/ListSet.v",
    "theorem_start_pos": {
      "line": 234,
      "column": 2
    },
    "theorem_end_pos": {
      "line": 235,
      "column": 66
    },
    "proof_start_pos": {
      "line": 236,
      "column": 2
    },
    "proof_end_pos": {
      "line": 240,
      "column": 6
    },
    "hash": "d3652997a88a64144b2e0c72a65256424250e335d651949ccae667b8d6dd023c"
  },
  {
    "project": {
      "dir_name": "mattam82-@@-Coq-misc",
      "split": {
        "dir_name": "train-sft-repos",
        "thm_dir_name": "train-sft-theorems"
      },
      "commit_hash": null,
      "compile_args": []
    },
    "path": "theories/Lists/ListSet.v",
    "theorem_start_pos": {
      "line": 244,
      "column": 2
    },
    "theorem_end_pos": {
      "line": 246,
      "column": 58
    },
    "proof_start_pos": {
      "line": 247,
      "column": 2
    },
    "proof_end_pos": {
      "line": 249,
      "column": 6
    },
    "hash": "d3652997a88a64144b2e0c72a65256424250e335d651949ccae667b8d6dd023c"
  },
  {
    "project": {
      "dir_name": "mattam82-@@-Coq-misc",
      "split": {
        "dir_name": "train-sft-repos",
        "thm_dir_name": "train-sft-theorems"
      },
      "commit_hash": null,
      "compile_args": []
    },
    "path": "theories/Lists/ListSet.v",
    "theorem_start_pos": {
      "line": 251,
      "column": 2
    },
    "theorem_end_pos": {
      "line": 253,
      "column": 58
    },
    "proof_start_pos": {
      "line": 254,
      "column": 2
    },
    "proof_end_pos": {
      "line": 262,
      "column": 6
    },
    "hash": "d3652997a88a64144b2e0c72a65256424250e335d651949ccae667b8d6dd023c"
  },
  {
    "project": {
      "dir_name": "mattam82-@@-Coq-misc",
      "split": {
        "dir_name": "train-sft-repos",
        "thm_dir_name": "train-sft-theorems"
      },
      "commit_hash": null,
      "compile_args": []
    },
    "path": "theories/Lists/ListSet.v",
    "theorem_start_pos": {
      "line": 264,
      "column": 2
    },
    "theorem_end_pos": {
      "line": 265,
      "column": 72
    },
    "proof_start_pos": {
      "line": 266,
      "column": 4
    },
    "proof_end_pos": {
      "line": 267,
      "column": 6
    },
    "hash": "d3652997a88a64144b2e0c72a65256424250e335d651949ccae667b8d6dd023c"
  },
  {
    "project": {
      "dir_name": "mattam82-@@-Coq-misc",
      "split": {
        "dir_name": "train-sft-repos",
        "thm_dir_name": "train-sft-theorems"
      },
      "commit_hash": null,
      "compile_args": []
    },
    "path": "theories/Lists/ListSet.v",
    "theorem_start_pos": {
      "line": 270,
      "column": 2
    },
    "theorem_end_pos": {
      "line": 271,
      "column": 72
    },
    "proof_start_pos": {
      "line": 272,
      "column": 4
    },
    "proof_end_pos": {
      "line": 273,
      "column": 6
    },
    "hash": "d3652997a88a64144b2e0c72a65256424250e335d651949ccae667b8d6dd023c"
  },
  {
    "project": {
      "dir_name": "mattam82-@@-Coq-misc",
      "split": {
        "dir_name": "train-sft-repos",
        "thm_dir_name": "train-sft-theorems"
      },
      "commit_hash": null,
      "compile_args": []
    },
    "path": "theories/Lists/ListSet.v",
    "theorem_start_pos": {
      "line": 276,
      "column": 2
    },
    "theorem_end_pos": {
      "line": 278,
      "column": 58
    },
    "proof_start_pos": {
      "line": 279,
      "column": 2
    },
    "proof_end_pos": {
      "line": 290,
      "column": 6
    },
    "hash": "d3652997a88a64144b2e0c72a65256424250e335d651949ccae667b8d6dd023c"
  },
  {
    "project": {
      "dir_name": "mattam82-@@-Coq-misc",
      "split": {
        "dir_name": "train-sft-repos",
        "thm_dir_name": "train-sft-theorems"
      },
      "commit_hash": null,
      "compile_args": []
    },
    "path": "theories/Lists/ListSet.v",
    "theorem_start_pos": {
      "line": 292,
      "column": 2
    },
    "theorem_end_pos": {
      "line": 293,
      "column": 66
    },
    "proof_start_pos": {
      "line": 294,
      "column": 2
    },
    "proof_end_pos": {
      "line": 302,
      "column": 6
    },
    "hash": "d3652997a88a64144b2e0c72a65256424250e335d651949ccae667b8d6dd023c"
  },
  {
    "project": {
      "dir_name": "mattam82-@@-Coq-misc",
      "split": {
        "dir_name": "train-sft-repos",
        "thm_dir_name": "train-sft-theorems"
      },
      "commit_hash": null,
      "compile_args": []
    },
    "path": "theories/Lists/ListSet.v",
    "theorem_start_pos": {
      "line": 304,
      "column": 2
    },
    "theorem_end_pos": {
      "line": 305,
      "column": 66
    },
    "proof_start_pos": {
      "line": 306,
      "column": 2
    },
    "proof_end_pos": {
      "line": 315,
      "column": 6
    },
    "hash": "d3652997a88a64144b2e0c72a65256424250e335d651949ccae667b8d6dd023c"
  },
  {
    "project": {
      "dir_name": "mattam82-@@-Coq-misc",
      "split": {
        "dir_name": "train-sft-repos",
        "thm_dir_name": "train-sft-theorems"
      },
      "commit_hash": null,
      "compile_args": []
    },
    "path": "theories/Lists/ListSet.v",
    "theorem_start_pos": {
      "line": 319,
      "column": 2
    },
    "theorem_end_pos": {
      "line": 321,
      "column": 58
    },
    "proof_start_pos": {
      "line": 322,
      "column": 2
    },
    "proof_end_pos": {
      "line": 324,
      "column": 6
    },
    "hash": "d3652997a88a64144b2e0c72a65256424250e335d651949ccae667b8d6dd023c"
  },
  {
    "project": {
      "dir_name": "mattam82-@@-Coq-misc",
      "split": {
        "dir_name": "train-sft-repos",
        "thm_dir_name": "train-sft-theorems"
      },
      "commit_hash": null,
      "compile_args": []
    },
    "path": "theories/Lists/ListSet.v",
    "theorem_start_pos": {
      "line": 326,
      "column": 2
    },
    "theorem_end_pos": {
      "line": 328,
      "column": 59
    },
    "proof_start_pos": {
      "line": 329,
      "column": 2
    },
    "proof_end_pos": {
      "line": 337,
      "column": 6
    },
    "hash": "d3652997a88a64144b2e0c72a65256424250e335d651949ccae667b8d6dd023c"
  },
  {
    "project": {
      "dir_name": "mattam82-@@-Coq-misc",
      "split": {
        "dir_name": "train-sft-repos",
        "thm_dir_name": "train-sft-theorems"
      },
      "commit_hash": null,
      "compile_args": []
    },
    "path": "theories/Lists/ListSet.v",
    "theorem_start_pos": {
      "line": 339,
      "column": 2
    },
    "theorem_end_pos": {
      "line": 340,
      "column": 65
    },
    "proof_start_pos": {
      "line": 341,
      "column": 2
    },
    "proof_end_pos": {
      "line": 348,
      "column": 6
    },
    "hash": "d3652997a88a64144b2e0c72a65256424250e335d651949ccae667b8d6dd023c"
  },
  {
    "project": {
      "dir_name": "mattam82-@@-Coq-misc",
      "split": {
        "dir_name": "train-sft-repos",
        "thm_dir_name": "train-sft-theorems"
      },
      "commit_hash": null,
      "compile_args": []
    },
    "path": "theories/Lists/ListSet.v",
    "theorem_start_pos": {
      "line": 350,
      "column": 2
    },
    "theorem_end_pos": {
      "line": 351,
      "column": 67
    },
    "proof_start_pos": {
      "line": 352,
      "column": 2
    },
    "proof_end_pos": {
      "line": 358,
      "column": 6
    },
    "hash": "d3652997a88a64144b2e0c72a65256424250e335d651949ccae667b8d6dd023c"
  },
  {
    "project": {
      "dir_name": "mattam82-@@-Coq-misc",
      "split": {
        "dir_name": "train-sft-repos",
        "thm_dir_name": "train-sft-theorems"
      },
      "commit_hash": null,
      "compile_args": []
    },
    "path": "theories/Lists/ListSet.v",
    "theorem_start_pos": {
      "line": 360,
      "column": 2
    },
    "theorem_end_pos": {
      "line": 360,
      "column": 75
    },
    "proof_start_pos": {
      "line": 361,
      "column": 2
    },
    "proof_end_pos": {
      "line": 364,
      "column": 6
    },
    "hash": "d3652997a88a64144b2e0c72a65256424250e335d651949ccae667b8d6dd023c"
  }
]