[
  {
    "project": {
      "dir_name": "gzholtkevych-@@-CertifiedProgramming",
      "split": {
        "dir_name": "train-rl-repos",
        "thm_dir_name": "train-rl-theorems"
      },
      "commit_hash": null,
      "compile_args": []
    },
    "path": "CoqScripts/NameSets.v",
    "theorem_start_pos": {
      "line": 127,
      "column": 2
    },
    "theorem_end_pos": {
      "line": 127,
      "column": 49
    },
    "proof_start_pos": {
      "line": 128,
      "column": 2
    },
    "proof_end_pos": {
      "line": 138,
      "column": 6
    },
    "hash": "f4250caab91059fcdc783cfd380bdce699d43c7eded34fadadb5c448e065936a"
  },
  {
    "project": {
      "dir_name": "gzholtkevych-@@-CertifiedProgramming",
      "split": {
        "dir_name": "train-rl-repos",
        "thm_dir_name": "train-rl-theorems"
      },
      "commit_hash": null,
      "compile_args": []
    },
    "path": "CoqScripts/NameSets.v",
    "theorem_start_pos": {
      "line": 140,
      "column": 2
    },
    "theorem_end_pos": {
      "line": 140,
      "column": 71
    },
    "proof_start_pos": {
      "line": 141,
      "column": 2
    },
    "proof_end_pos": {
      "line": 156,
      "column": 6
    },
    "hash": "f4250caab91059fcdc783cfd380bdce699d43c7eded34fadadb5c448e065936a"
  },
  {
    "project": {
      "dir_name": "gzholtkevych-@@-CertifiedProgramming",
      "split": {
        "dir_name": "train-rl-repos",
        "thm_dir_name": "train-rl-theorems"
      },
      "commit_hash": null,
      "compile_args": []
    },
    "path": "CoqScripts/NameSets.v",
    "theorem_start_pos": {
      "line": 158,
      "column": 2
    },
    "theorem_end_pos": {
      "line": 158,
      "column": 72
    },
    "proof_start_pos": {
      "line": 159,
      "column": 2
    },
    "proof_end_pos": {
      "line": 172,
      "column": 6
    },
    "hash": "f4250caab91059fcdc783cfd380bdce699d43c7eded34fadadb5c448e065936a"
  },
  {
    "project": {
      "dir_name": "gzholtkevych-@@-CertifiedProgramming",
      "split": {
        "dir_name": "train-rl-repos",
        "thm_dir_name": "train-rl-theorems"
      },
      "commit_hash": null,
      "compile_args": []
    },
    "path": "CoqScripts/NameSets.v",
    "theorem_start_pos": {
      "line": 180,
      "column": 2
    },
    "theorem_end_pos": {
      "line": 180,
      "column": 62
    },
    "proof_start_pos": {
      "line": 181,
      "column": 2
    },
    "proof_end_pos": {
      "line": 198,
      "column": 6
    },
    "hash": "f4250caab91059fcdc783cfd380bdce699d43c7eded34fadadb5c448e065936a"
  },
  {
    "project": {
      "dir_name": "gzholtkevych-@@-CertifiedProgramming",
      "split": {
        "dir_name": "train-rl-repos",
        "thm_dir_name": "train-rl-theorems"
      },
      "commit_hash": null,
      "compile_args": []
    },
    "path": "CoqScripts/NameSets.v",
    "theorem_start_pos": {
      "line": 207,
      "column": 2
    },
    "theorem_end_pos": {
      "line": 207,
      "column": 51
    },
    "proof_start_pos": {
      "line": 208,
      "column": 2
    },
    "proof_end_pos": {
      "line": 208,
      "column": 77
    },
    "hash": "f4250caab91059fcdc783cfd380bdce699d43c7eded34fadadb5c448e065936a"
  },
  {
    "project": {
      "dir_name": "gzholtkevych-@@-CertifiedProgramming",
      "split": {
        "dir_name": "train-rl-repos",
        "thm_dir_name": "train-rl-theorems"
      },
      "commit_hash": null,
      "compile_args": []
    },
    "path": "CoqScripts/NameSets.v",
    "theorem_start_pos": {
      "line": 210,
      "column": 2
    },
    "theorem_end_pos": {
      "line": 210,
      "column": 50
    },
    "proof_start_pos": {
      "line": 211,
      "column": 2
    },
    "proof_end_pos": {
      "line": 211,
      "column": 38
    },
    "hash": "f4250caab91059fcdc783cfd380bdce699d43c7eded34fadadb5c448e065936a"
  }
]