[
  {
    "project": {
      "dir_name": "ComputerAidedLL-@@-PowerWebster_ILL",
      "split": {
        "dir_name": "train-rl-repos",
        "thm_dir_name": "train-rl-theorems"
      },
      "commit_hash": null,
      "compile_args": []
    },
    "path": "blocks.v",
    "theorem_start_pos": {
      "line": 49,
      "column": 0
    },
    "theorem_end_pos": {
      "line": 51,
      "column": 67
    },
    "proof_start_pos": {
      "line": 52,
      "column": 0
    },
    "proof_end_pos": {
      "line": 65,
      "column": 4
    },
    "hash": "2f5ea57a08aadc99f00a6f9b57dd4b1b90cfb2663b42a67f1100174b59d58509"
  },
  {
    "project": {
      "dir_name": "ComputerAidedLL-@@-PowerWebster_ILL",
      "split": {
        "dir_name": "train-rl-repos",
        "thm_dir_name": "train-rl-theorems"
      },
      "commit_hash": null,
      "compile_args": []
    },
    "path": "blocks.v",
    "theorem_start_pos": {
      "line": 68,
      "column": 0
    },
    "theorem_end_pos": {
      "line": 70,
      "column": 54
    },
    "proof_start_pos": {
      "line": 71,
      "column": 0
    },
    "proof_end_pos": {
      "line": 82,
      "column": 4
    },
    "hash": "2f5ea57a08aadc99f00a6f9b57dd4b1b90cfb2663b42a67f1100174b59d58509"
  },
  {
    "project": {
      "dir_name": "ComputerAidedLL-@@-PowerWebster_ILL",
      "split": {
        "dir_name": "train-rl-repos",
        "thm_dir_name": "train-rl-theorems"
      },
      "commit_hash": null,
      "compile_args": []
    },
    "path": "blocks.v",
    "theorem_start_pos": {
      "line": 85,
      "column": 0
    },
    "theorem_end_pos": {
      "line": 87,
      "column": 66
    },
    "proof_start_pos": {
      "line": 88,
      "column": 0
    },
    "proof_end_pos": {
      "line": 101,
      "column": 4
    },
    "hash": "2f5ea57a08aadc99f00a6f9b57dd4b1b90cfb2663b42a67f1100174b59d58509"
  },
  {
    "project": {
      "dir_name": "ComputerAidedLL-@@-PowerWebster_ILL",
      "split": {
        "dir_name": "train-rl-repos",
        "thm_dir_name": "train-rl-theorems"
      },
      "commit_hash": null,
      "compile_args": []
    },
    "path": "blocks.v",
    "theorem_start_pos": {
      "line": 104,
      "column": 0
    },
    "theorem_end_pos": {
      "line": 106,
      "column": 51
    },
    "proof_start_pos": {
      "line": 107,
      "column": 0
    },
    "proof_end_pos": {
      "line": 120,
      "column": 4
    },
    "hash": "2f5ea57a08aadc99f00a6f9b57dd4b1b90cfb2663b42a67f1100174b59d58509"
  },
  {
    "project": {
      "dir_name": "ComputerAidedLL-@@-PowerWebster_ILL",
      "split": {
        "dir_name": "train-rl-repos",
        "thm_dir_name": "train-rl-theorems"
      },
      "commit_hash": null,
      "compile_args": []
    },
    "path": "blocks.v",
    "theorem_start_pos": {
      "line": 143,
      "column": 0
    },
    "theorem_end_pos": {
      "line": 145,
      "column": 52
    },
    "proof_start_pos": {
      "line": 146,
      "column": 0
    },
    "proof_end_pos": {
      "line": 150,
      "column": 4
    },
    "hash": "2f5ea57a08aadc99f00a6f9b57dd4b1b90cfb2663b42a67f1100174b59d58509"
  },
  {
    "project": {
      "dir_name": "ComputerAidedLL-@@-PowerWebster_ILL",
      "split": {
        "dir_name": "train-rl-repos",
        "thm_dir_name": "train-rl-theorems"
      },
      "commit_hash": null,
      "compile_args": []
    },
    "path": "blocks.v",
    "theorem_start_pos": {
      "line": 153,
      "column": 0
    },
    "theorem_end_pos": {
      "line": 155,
      "column": 45
    },
    "proof_start_pos": {
      "line": 156,
      "column": 0
    },
    "proof_end_pos": {
      "line": 160,
      "column": 4
    },
    "hash": "2f5ea57a08aadc99f00a6f9b57dd4b1b90cfb2663b42a67f1100174b59d58509"
  },
  {
    "project": {
      "dir_name": "ComputerAidedLL-@@-PowerWebster_ILL",
      "split": {
        "dir_name": "train-rl-repos",
        "thm_dir_name": "train-rl-theorems"
      },
      "commit_hash": null,
      "compile_args": []
    },
    "path": "blocks.v",
    "theorem_start_pos": {
      "line": 163,
      "column": 0
    },
    "theorem_end_pos": {
      "line": 165,
      "column": 65
    },
    "proof_start_pos": {
      "line": 166,
      "column": 0
    },
    "proof_end_pos": {
      "line": 173,
      "column": 4
    },
    "hash": "2f5ea57a08aadc99f00a6f9b57dd4b1b90cfb2663b42a67f1100174b59d58509"
  },
  {
    "project": {
      "dir_name": "ComputerAidedLL-@@-PowerWebster_ILL",
      "split": {
        "dir_name": "train-rl-repos",
        "thm_dir_name": "train-rl-theorems"
      },
      "commit_hash": null,
      "compile_args": []
    },
    "path": "blocks.v",
    "theorem_start_pos": {
      "line": 176,
      "column": 0
    },
    "theorem_end_pos": {
      "line": 178,
      "column": 45
    },
    "proof_start_pos": {
      "line": 179,
      "column": 0
    },
    "proof_end_pos": {
      "line": 186,
      "column": 4
    },
    "hash": "2f5ea57a08aadc99f00a6f9b57dd4b1b90cfb2663b42a67f1100174b59d58509"
  },
  {
    "project": {
      "dir_name": "ComputerAidedLL-@@-PowerWebster_ILL",
      "split": {
        "dir_name": "train-rl-repos",
        "thm_dir_name": "train-rl-theorems"
      },
      "commit_hash": null,
      "compile_args": []
    },
    "path": "blocks.v",
    "theorem_start_pos": {
      "line": 189,
      "column": 0
    },
    "theorem_end_pos": {
      "line": 191,
      "column": 51
    },
    "proof_start_pos": {
      "line": 192,
      "column": 0
    },
    "proof_end_pos": {
      "line": 201,
      "column": 4
    },
    "hash": "2f5ea57a08aadc99f00a6f9b57dd4b1b90cfb2663b42a67f1100174b59d58509"
  },
  {
    "project": {
      "dir_name": "ComputerAidedLL-@@-PowerWebster_ILL",
      "split": {
        "dir_name": "train-rl-repos",
        "thm_dir_name": "train-rl-theorems"
      },
      "commit_hash": null,
      "compile_args": []
    },
    "path": "blocks.v",
    "theorem_start_pos": {
      "line": 204,
      "column": 0
    },
    "theorem_end_pos": {
      "line": 206,
      "column": 20
    },
    "proof_start_pos": {
      "line": 207,
      "column": 0
    },
    "proof_end_pos": {
      "line": 213,
      "column": 4
    },
    "hash": "2f5ea57a08aadc99f00a6f9b57dd4b1b90cfb2663b42a67f1100174b59d58509"
  },
  {
    "project": {
      "dir_name": "ComputerAidedLL-@@-PowerWebster_ILL",
      "split": {
        "dir_name": "train-rl-repos",
        "thm_dir_name": "train-rl-theorems"
      },
      "commit_hash": null,
      "compile_args": []
    },
    "path": "blocks.v",
    "theorem_start_pos": {
      "line": 218,
      "column": 0
    },
    "theorem_end_pos": {
      "line": 221,
      "column": 20
    },
    "proof_start_pos": {
      "line": 222,
      "column": 0
    },
    "proof_end_pos": {
      "line": 234,
      "column": 4
    },
    "hash": "2f5ea57a08aadc99f00a6f9b57dd4b1b90cfb2663b42a67f1100174b59d58509"
  }
]