[
  {
    "project": {
      "dir_name": "hyleIndex-@@-sort-and-regular-exp",
      "split": {
        "dir_name": "train-rl-repos",
        "thm_dir_name": "train-rl-theorems"
      },
      "commit_hash": null,
      "compile_args": []
    },
    "path": "regexp.v",
    "theorem_start_pos": {
      "line": 159,
      "column": 0
    },
    "theorem_end_pos": {
      "line": 159,
      "column": 42
    },
    "proof_start_pos": {
      "line": 160,
      "column": 0
    },
    "proof_end_pos": {
      "line": 172,
      "column": 4
    },
    "hash": "4ed805e796c07b3be35aa489edde76bd0fb072c80f3ccc7e68f85f16e7b7cad4"
  },
  {
    "project": {
      "dir_name": "hyleIndex-@@-sort-and-regular-exp",
      "split": {
        "dir_name": "train-rl-repos",
        "thm_dir_name": "train-rl-theorems"
      },
      "commit_hash": null,
      "compile_args": []
    },
    "path": "regexp.v",
    "theorem_start_pos": {
      "line": 174,
      "column": 0
    },
    "theorem_end_pos": {
      "line": 174,
      "column": 42
    },
    "proof_start_pos": {
      "line": 175,
      "column": 0
    },
    "proof_end_pos": {
      "line": 187,
      "column": 4
    },
    "hash": "4ed805e796c07b3be35aa489edde76bd0fb072c80f3ccc7e68f85f16e7b7cad4"
  },
  {
    "project": {
      "dir_name": "hyleIndex-@@-sort-and-regular-exp",
      "split": {
        "dir_name": "train-rl-repos",
        "thm_dir_name": "train-rl-theorems"
      },
      "commit_hash": null,
      "compile_args": []
    },
    "path": "regexp.v",
    "theorem_start_pos": {
      "line": 189,
      "column": 0
    },
    "theorem_end_pos": {
      "line": 189,
      "column": 38
    },
    "proof_start_pos": {
      "line": 190,
      "column": 0
    },
    "proof_end_pos": {
      "line": 211,
      "column": 4
    },
    "hash": "4ed805e796c07b3be35aa489edde76bd0fb072c80f3ccc7e68f85f16e7b7cad4"
  },
  {
    "project": {
      "dir_name": "hyleIndex-@@-sort-and-regular-exp",
      "split": {
        "dir_name": "train-rl-repos",
        "thm_dir_name": "train-rl-theorems"
      },
      "commit_hash": null,
      "compile_args": []
    },
    "path": "regexp.v",
    "theorem_start_pos": {
      "line": 213,
      "column": 0
    },
    "theorem_end_pos": {
      "line": 213,
      "column": 38
    },
    "proof_start_pos": {
      "line": 214,
      "column": 0
    },
    "proof_end_pos": {
      "line": 235,
      "column": 4
    },
    "hash": "4ed805e796c07b3be35aa489edde76bd0fb072c80f3ccc7e68f85f16e7b7cad4"
  },
  {
    "project": {
      "dir_name": "hyleIndex-@@-sort-and-regular-exp",
      "split": {
        "dir_name": "train-rl-repos",
        "thm_dir_name": "train-rl-theorems"
      },
      "commit_hash": null,
      "compile_args": []
    },
    "path": "regexp.v",
    "theorem_start_pos": {
      "line": 237,
      "column": 0
    },
    "theorem_end_pos": {
      "line": 237,
      "column": 65
    },
    "proof_start_pos": {
      "line": 238,
      "column": 0
    },
    "proof_end_pos": {
      "line": 287,
      "column": 4
    },
    "hash": "4ed805e796c07b3be35aa489edde76bd0fb072c80f3ccc7e68f85f16e7b7cad4"
  },
  {
    "project": {
      "dir_name": "hyleIndex-@@-sort-and-regular-exp",
      "split": {
        "dir_name": "train-rl-repos",
        "thm_dir_name": "train-rl-theorems"
      },
      "commit_hash": null,
      "compile_args": []
    },
    "path": "regexp.v",
    "theorem_start_pos": {
      "line": 289,
      "column": 0
    },
    "theorem_end_pos": {
      "line": 289,
      "column": 42
    },
    "proof_start_pos": {
      "line": 290,
      "column": 0
    },
    "proof_end_pos": {
      "line": 303,
      "column": 4
    },
    "hash": "4ed805e796c07b3be35aa489edde76bd0fb072c80f3ccc7e68f85f16e7b7cad4"
  },
  {
    "project": {
      "dir_name": "hyleIndex-@@-sort-and-regular-exp",
      "split": {
        "dir_name": "train-rl-repos",
        "thm_dir_name": "train-rl-theorems"
      },
      "commit_hash": null,
      "compile_args": []
    },
    "path": "regexp.v",
    "theorem_start_pos": {
      "line": 307,
      "column": 0
    },
    "theorem_end_pos": {
      "line": 307,
      "column": 42
    },
    "proof_start_pos": {
      "line": 308,
      "column": 0
    },
    "proof_end_pos": {
      "line": 319,
      "column": 4
    },
    "hash": "4ed805e796c07b3be35aa489edde76bd0fb072c80f3ccc7e68f85f16e7b7cad4"
  },
  {
    "project": {
      "dir_name": "hyleIndex-@@-sort-and-regular-exp",
      "split": {
        "dir_name": "train-rl-repos",
        "thm_dir_name": "train-rl-theorems"
      },
      "commit_hash": null,
      "compile_args": []
    },
    "path": "regexp.v",
    "theorem_start_pos": {
      "line": 321,
      "column": 0
    },
    "theorem_end_pos": {
      "line": 321,
      "column": 44
    },
    "proof_start_pos": {
      "line": 322,
      "column": 0
    },
    "proof_end_pos": {
      "line": 336,
      "column": 4
    },
    "hash": "4ed805e796c07b3be35aa489edde76bd0fb072c80f3ccc7e68f85f16e7b7cad4"
  },
  {
    "project": {
      "dir_name": "hyleIndex-@@-sort-and-regular-exp",
      "split": {
        "dir_name": "train-rl-repos",
        "thm_dir_name": "train-rl-theorems"
      },
      "commit_hash": null,
      "compile_args": []
    },
    "path": "regexp.v",
    "theorem_start_pos": {
      "line": 376,
      "column": 0
    },
    "theorem_end_pos": {
      "line": 376,
      "column": 76
    },
    "proof_start_pos": {
      "line": 377,
      "column": 0
    },
    "proof_end_pos": {
      "line": 401,
      "column": 4
    },
    "hash": "4ed805e796c07b3be35aa489edde76bd0fb072c80f3ccc7e68f85f16e7b7cad4"
  },
  {
    "project": {
      "dir_name": "hyleIndex-@@-sort-and-regular-exp",
      "split": {
        "dir_name": "train-rl-repos",
        "thm_dir_name": "train-rl-theorems"
      },
      "commit_hash": null,
      "compile_args": []
    },
    "path": "regexp.v",
    "theorem_start_pos": {
      "line": 403,
      "column": 0
    },
    "theorem_end_pos": {
      "line": 403,
      "column": 37
    },
    "proof_start_pos": {
      "line": 404,
      "column": 0
    },
    "proof_end_pos": {
      "line": 412,
      "column": 4
    },
    "hash": "4ed805e796c07b3be35aa489edde76bd0fb072c80f3ccc7e68f85f16e7b7cad4"
  },
  {
    "project": {
      "dir_name": "hyleIndex-@@-sort-and-regular-exp",
      "split": {
        "dir_name": "train-rl-repos",
        "thm_dir_name": "train-rl-theorems"
      },
      "commit_hash": null,
      "compile_args": []
    },
    "path": "regexp.v",
    "theorem_start_pos": {
      "line": 417,
      "column": 0
    },
    "theorem_end_pos": {
      "line": 417,
      "column": 48
    },
    "proof_start_pos": {
      "line": 418,
      "column": 0
    },
    "proof_end_pos": {
      "line": 427,
      "column": 4
    },
    "hash": "4ed805e796c07b3be35aa489edde76bd0fb072c80f3ccc7e68f85f16e7b7cad4"
  },
  {
    "project": {
      "dir_name": "hyleIndex-@@-sort-and-regular-exp",
      "split": {
        "dir_name": "train-rl-repos",
        "thm_dir_name": "train-rl-theorems"
      },
      "commit_hash": null,
      "compile_args": []
    },
    "path": "regexp.v",
    "theorem_start_pos": {
      "line": 430,
      "column": 0
    },
    "theorem_end_pos": {
      "line": 430,
      "column": 38
    },
    "proof_start_pos": {
      "line": 431,
      "column": 0
    },
    "proof_end_pos": {
      "line": 438,
      "column": 4
    },
    "hash": "4ed805e796c07b3be35aa489edde76bd0fb072c80f3ccc7e68f85f16e7b7cad4"
  },
  {
    "project": {
      "dir_name": "hyleIndex-@@-sort-and-regular-exp",
      "split": {
        "dir_name": "train-rl-repos",
        "thm_dir_name": "train-rl-theorems"
      },
      "commit_hash": null,
      "compile_args": []
    },
    "path": "regexp.v",
    "theorem_start_pos": {
      "line": 440,
      "column": 0
    },
    "theorem_end_pos": {
      "line": 440,
      "column": 38
    },
    "proof_start_pos": {
      "line": 441,
      "column": 0
    },
    "proof_end_pos": {
      "line": 453,
      "column": 4
    },
    "hash": "4ed805e796c07b3be35aa489edde76bd0fb072c80f3ccc7e68f85f16e7b7cad4"
  },
  {
    "project": {
      "dir_name": "hyleIndex-@@-sort-and-regular-exp",
      "split": {
        "dir_name": "train-rl-repos",
        "thm_dir_name": "train-rl-theorems"
      },
      "commit_hash": null,
      "compile_args": []
    },
    "path": "regexp.v",
    "theorem_start_pos": {
      "line": 455,
      "column": 0
    },
    "theorem_end_pos": {
      "line": 455,
      "column": 45
    },
    "proof_start_pos": {
      "line": 456,
      "column": 0
    },
    "proof_end_pos": {
      "line": 468,
      "column": 4
    },
    "hash": "4ed805e796c07b3be35aa489edde76bd0fb072c80f3ccc7e68f85f16e7b7cad4"
  },
  {
    "project": {
      "dir_name": "hyleIndex-@@-sort-and-regular-exp",
      "split": {
        "dir_name": "train-rl-repos",
        "thm_dir_name": "train-rl-theorems"
      },
      "commit_hash": null,
      "compile_args": []
    },
    "path": "regexp.v",
    "theorem_start_pos": {
      "line": 470,
      "column": 0
    },
    "theorem_end_pos": {
      "line": 470,
      "column": 74
    },
    "proof_start_pos": {
      "line": 471,
      "column": 0
    },
    "proof_end_pos": {
      "line": 508,
      "column": 4
    },
    "hash": "4ed805e796c07b3be35aa489edde76bd0fb072c80f3ccc7e68f85f16e7b7cad4"
  },
  {
    "project": {
      "dir_name": "hyleIndex-@@-sort-and-regular-exp",
      "split": {
        "dir_name": "train-rl-repos",
        "thm_dir_name": "train-rl-theorems"
      },
      "commit_hash": null,
      "compile_args": []
    },
    "path": "regexp.v",
    "theorem_start_pos": {
      "line": 510,
      "column": 0
    },
    "theorem_end_pos": {
      "line": 510,
      "column": 62
    },
    "proof_start_pos": {
      "line": 511,
      "column": 0
    },
    "proof_end_pos": {
      "line": 522,
      "column": 4
    },
    "hash": "4ed805e796c07b3be35aa489edde76bd0fb072c80f3ccc7e68f85f16e7b7cad4"
  },
  {
    "project": {
      "dir_name": "hyleIndex-@@-sort-and-regular-exp",
      "split": {
        "dir_name": "train-rl-repos",
        "thm_dir_name": "train-rl-theorems"
      },
      "commit_hash": null,
      "compile_args": []
    },
    "path": "regexp.v",
    "theorem_start_pos": {
      "line": 525,
      "column": 0
    },
    "theorem_end_pos": {
      "line": 525,
      "column": 54
    },
    "proof_start_pos": {
      "line": 526,
      "column": 0
    },
    "proof_end_pos": {
      "line": 545,
      "column": 4
    },
    "hash": "4ed805e796c07b3be35aa489edde76bd0fb072c80f3ccc7e68f85f16e7b7cad4"
  },
  {
    "project": {
      "dir_name": "hyleIndex-@@-sort-and-regular-exp",
      "split": {
        "dir_name": "train-rl-repos",
        "thm_dir_name": "train-rl-theorems"
      },
      "commit_hash": null,
      "compile_args": []
    },
    "path": "regexp.v",
    "theorem_start_pos": {
      "line": 547,
      "column": 0
    },
    "theorem_end_pos": {
      "line": 547,
      "column": 50
    },
    "proof_start_pos": {
      "line": 548,
      "column": 0
    },
    "proof_end_pos": {
      "line": 576,
      "column": 4
    },
    "hash": "4ed805e796c07b3be35aa489edde76bd0fb072c80f3ccc7e68f85f16e7b7cad4"
  },
  {
    "project": {
      "dir_name": "hyleIndex-@@-sort-and-regular-exp",
      "split": {
        "dir_name": "train-rl-repos",
        "thm_dir_name": "train-rl-theorems"
      },
      "commit_hash": null,
      "compile_args": []
    },
    "path": "regexp.v",
    "theorem_start_pos": {
      "line": 655,
      "column": 0
    },
    "theorem_end_pos": {
      "line": 655,
      "column": 44
    },
    "proof_start_pos": {
      "line": 656,
      "column": 0
    },
    "proof_end_pos": {
      "line": 665,
      "column": 4
    },
    "hash": "4ed805e796c07b3be35aa489edde76bd0fb072c80f3ccc7e68f85f16e7b7cad4"
  },
  {
    "project": {
      "dir_name": "hyleIndex-@@-sort-and-regular-exp",
      "split": {
        "dir_name": "train-rl-repos",
        "thm_dir_name": "train-rl-theorems"
      },
      "commit_hash": null,
      "compile_args": []
    },
    "path": "regexp.v",
    "theorem_start_pos": {
      "line": 670,
      "column": 0
    },
    "theorem_end_pos": {
      "line": 670,
      "column": 79
    },
    "proof_start_pos": {
      "line": 671,
      "column": 0
    },
    "proof_end_pos": {
      "line": 689,
      "column": 4
    },
    "hash": "4ed805e796c07b3be35aa489edde76bd0fb072c80f3ccc7e68f85f16e7b7cad4"
  },
  {
    "project": {
      "dir_name": "hyleIndex-@@-sort-and-regular-exp",
      "split": {
        "dir_name": "train-rl-repos",
        "thm_dir_name": "train-rl-theorems"
      },
      "commit_hash": null,
      "compile_args": []
    },
    "path": "regexp.v",
    "theorem_start_pos": {
      "line": 691,
      "column": 0
    },
    "theorem_end_pos": {
      "line": 691,
      "column": 79
    },
    "proof_start_pos": {
      "line": 692,
      "column": 0
    },
    "proof_end_pos": {
      "line": 719,
      "column": 4
    },
    "hash": "4ed805e796c07b3be35aa489edde76bd0fb072c80f3ccc7e68f85f16e7b7cad4"
  },
  {
    "project": {
      "dir_name": "hyleIndex-@@-sort-and-regular-exp",
      "split": {
        "dir_name": "train-rl-repos",
        "thm_dir_name": "train-rl-theorems"
      },
      "commit_hash": null,
      "compile_args": []
    },
    "path": "regexp.v",
    "theorem_start_pos": {
      "line": 721,
      "column": 0
    },
    "theorem_end_pos": {
      "line": 721,
      "column": 49
    },
    "proof_start_pos": {
      "line": 722,
      "column": 0
    },
    "proof_end_pos": {
      "line": 744,
      "column": 4
    },
    "hash": "4ed805e796c07b3be35aa489edde76bd0fb072c80f3ccc7e68f85f16e7b7cad4"
  },
  {
    "project": {
      "dir_name": "hyleIndex-@@-sort-and-regular-exp",
      "split": {
        "dir_name": "train-rl-repos",
        "thm_dir_name": "train-rl-theorems"
      },
      "commit_hash": null,
      "compile_args": []
    },
    "path": "regexp.v",
    "theorem_start_pos": {
      "line": 746,
      "column": 0
    },
    "theorem_end_pos": {
      "line": 746,
      "column": 62
    },
    "proof_start_pos": {
      "line": 747,
      "column": 0
    },
    "proof_end_pos": {
      "line": 797,
      "column": 4
    },
    "hash": "4ed805e796c07b3be35aa489edde76bd0fb072c80f3ccc7e68f85f16e7b7cad4"
  },
  {
    "project": {
      "dir_name": "hyleIndex-@@-sort-and-regular-exp",
      "split": {
        "dir_name": "train-rl-repos",
        "thm_dir_name": "train-rl-theorems"
      },
      "commit_hash": null,
      "compile_args": []
    },
    "path": "regexp.v",
    "theorem_start_pos": {
      "line": 812,
      "column": 0
    },
    "theorem_end_pos": {
      "line": 812,
      "column": 83
    },
    "proof_start_pos": {
      "line": 813,
      "column": 0
    },
    "proof_end_pos": {
      "line": 825,
      "column": 4
    },
    "hash": "4ed805e796c07b3be35aa489edde76bd0fb072c80f3ccc7e68f85f16e7b7cad4"
  },
  {
    "project": {
      "dir_name": "hyleIndex-@@-sort-and-regular-exp",
      "split": {
        "dir_name": "train-rl-repos",
        "thm_dir_name": "train-rl-theorems"
      },
      "commit_hash": null,
      "compile_args": []
    },
    "path": "regexp.v",
    "theorem_start_pos": {
      "line": 827,
      "column": 0
    },
    "theorem_end_pos": {
      "line": 827,
      "column": 133
    },
    "proof_start_pos": {
      "line": 828,
      "column": 0
    },
    "proof_end_pos": {
      "line": 898,
      "column": 4
    },
    "hash": "4ed805e796c07b3be35aa489edde76bd0fb072c80f3ccc7e68f85f16e7b7cad4"
  },
  {
    "project": {
      "dir_name": "hyleIndex-@@-sort-and-regular-exp",
      "split": {
        "dir_name": "train-rl-repos",
        "thm_dir_name": "train-rl-theorems"
      },
      "commit_hash": null,
      "compile_args": []
    },
    "path": "regexp.v",
    "theorem_start_pos": {
      "line": 940,
      "column": 0
    },
    "theorem_end_pos": {
      "line": 940,
      "column": 52
    },
    "proof_start_pos": {
      "line": 941,
      "column": 0
    },
    "proof_end_pos": {
      "line": 1006,
      "column": 4
    },
    "hash": "4ed805e796c07b3be35aa489edde76bd0fb072c80f3ccc7e68f85f16e7b7cad4"
  },
  {
    "project": {
      "dir_name": "hyleIndex-@@-sort-and-regular-exp",
      "split": {
        "dir_name": "train-rl-repos",
        "thm_dir_name": "train-rl-theorems"
      },
      "commit_hash": null,
      "compile_args": []
    },
    "path": "regexp.v",
    "theorem_start_pos": {
      "line": 1064,
      "column": 0
    },
    "theorem_end_pos": {
      "line": 1065,
      "column": 49
    },
    "proof_start_pos": {
      "line": 1066,
      "column": 0
    },
    "proof_end_pos": {
      "line": 1148,
      "column": 4
    },
    "hash": "4ed805e796c07b3be35aa489edde76bd0fb072c80f3ccc7e68f85f16e7b7cad4"
  },
  {
    "project": {
      "dir_name": "hyleIndex-@@-sort-and-regular-exp",
      "split": {
        "dir_name": "train-rl-repos",
        "thm_dir_name": "train-rl-theorems"
      },
      "commit_hash": null,
      "compile_args": []
    },
    "path": "regexp.v",
    "theorem_start_pos": {
      "line": 1152,
      "column": 0
    },
    "theorem_end_pos": {
      "line": 1153,
      "column": 27
    },
    "proof_start_pos": {
      "line": 1154,
      "column": 0
    },
    "proof_end_pos": {
      "line": 1164,
      "column": 4
    },
    "hash": "4ed805e796c07b3be35aa489edde76bd0fb072c80f3ccc7e68f85f16e7b7cad4"
  },
  {
    "project": {
      "dir_name": "hyleIndex-@@-sort-and-regular-exp",
      "split": {
        "dir_name": "train-rl-repos",
        "thm_dir_name": "train-rl-theorems"
      },
      "commit_hash": null,
      "compile_args": []
    },
    "path": "regexp.v",
    "theorem_start_pos": {
      "line": 1168,
      "column": 0
    },
    "theorem_end_pos": {
      "line": 1169,
      "column": 50
    },
    "proof_start_pos": {
      "line": 1170,
      "column": 0
    },
    "proof_end_pos": {
      "line": 1292,
      "column": 4
    },
    "hash": "4ed805e796c07b3be35aa489edde76bd0fb072c80f3ccc7e68f85f16e7b7cad4"
  },
  {
    "project": {
      "dir_name": "hyleIndex-@@-sort-and-regular-exp",
      "split": {
        "dir_name": "train-rl-repos",
        "thm_dir_name": "train-rl-theorems"
      },
      "commit_hash": null,
      "compile_args": []
    },
    "path": "regexp.v",
    "theorem_start_pos": {
      "line": 1294,
      "column": 0
    },
    "theorem_end_pos": {
      "line": 1295,
      "column": 27
    },
    "proof_start_pos": {
      "line": 1296,
      "column": 0
    },
    "proof_end_pos": {
      "line": 1308,
      "column": 4
    },
    "hash": "4ed805e796c07b3be35aa489edde76bd0fb072c80f3ccc7e68f85f16e7b7cad4"
  }
]