[
  {
    "project": {
      "dir_name": "lucasrsv-@@-taes",
      "split": {
        "dir_name": "train-rl-repos",
        "thm_dir_name": "train-rl-theorems"
      },
      "commit_hash": null,
      "compile_args": []
    },
    "path": "Basics.v",
    "theorem_start_pos": {
      "line": 921,
      "column": 0
    },
    "theorem_end_pos": {
      "line": 921,
      "column": 45
    },
    "proof_start_pos": {
      "line": 922,
      "column": 0
    },
    "proof_end_pos": {
      "line": 923,
      "column": 37
    },
    "hash": "c418596d9a77f4dc084423190048f67c07dbba1c07d96ed136e5a9c8026a3566"
  },
  {
    "project": {
      "dir_name": "lucasrsv-@@-taes",
      "split": {
        "dir_name": "train-rl-repos",
        "thm_dir_name": "train-rl-theorems"
      },
      "commit_hash": null,
      "compile_args": []
    },
    "path": "Basics.v",
    "theorem_start_pos": {
      "line": 941,
      "column": 0
    },
    "theorem_end_pos": {
      "line": 941,
      "column": 46
    },
    "proof_start_pos": {
      "line": 942,
      "column": 0
    },
    "proof_end_pos": {
      "line": 943,
      "column": 29
    },
    "hash": "c418596d9a77f4dc084423190048f67c07dbba1c07d96ed136e5a9c8026a3566"
  },
  {
    "project": {
      "dir_name": "lucasrsv-@@-taes",
      "split": {
        "dir_name": "train-rl-repos",
        "thm_dir_name": "train-rl-theorems"
      },
      "commit_hash": null,
      "compile_args": []
    },
    "path": "Basics.v",
    "theorem_start_pos": {
      "line": 974,
      "column": 0
    },
    "theorem_end_pos": {
      "line": 974,
      "column": 47
    },
    "proof_start_pos": {
      "line": 975,
      "column": 0
    },
    "proof_end_pos": {
      "line": 976,
      "column": 29
    },
    "hash": "c418596d9a77f4dc084423190048f67c07dbba1c07d96ed136e5a9c8026a3566"
  },
  {
    "project": {
      "dir_name": "lucasrsv-@@-taes",
      "split": {
        "dir_name": "train-rl-repos",
        "thm_dir_name": "train-rl-theorems"
      },
      "commit_hash": null,
      "compile_args": []
    },
    "path": "Basics.v",
    "theorem_start_pos": {
      "line": 986,
      "column": 0
    },
    "theorem_end_pos": {
      "line": 986,
      "column": 45
    },
    "proof_start_pos": {
      "line": 987,
      "column": 0
    },
    "proof_end_pos": {
      "line": 988,
      "column": 30
    },
    "hash": "c418596d9a77f4dc084423190048f67c07dbba1c07d96ed136e5a9c8026a3566"
  },
  {
    "project": {
      "dir_name": "lucasrsv-@@-taes",
      "split": {
        "dir_name": "train-rl-repos",
        "thm_dir_name": "train-rl-theorems"
      },
      "commit_hash": null,
      "compile_args": []
    },
    "path": "Basics.v",
    "theorem_start_pos": {
      "line": 990,
      "column": 0
    },
    "theorem_end_pos": {
      "line": 990,
      "column": 43
    },
    "proof_start_pos": {
      "line": 991,
      "column": 0
    },
    "proof_end_pos": {
      "line": 992,
      "column": 30
    },
    "hash": "c418596d9a77f4dc084423190048f67c07dbba1c07d96ed136e5a9c8026a3566"
  },
  {
    "project": {
      "dir_name": "lucasrsv-@@-taes",
      "split": {
        "dir_name": "train-rl-repos",
        "thm_dir_name": "train-rl-theorems"
      },
      "commit_hash": null,
      "compile_args": []
    },
    "path": "Basics.v",
    "theorem_start_pos": {
      "line": 1008,
      "column": 0
    },
    "theorem_end_pos": {
      "line": 1010,
      "column": 16
    },
    "proof_start_pos": {
      "line": 1028,
      "column": 0
    },
    "proof_end_pos": {
      "line": 1035,
      "column": 20
    },
    "hash": "c418596d9a77f4dc084423190048f67c07dbba1c07d96ed136e5a9c8026a3566"
  },
  {
    "project": {
      "dir_name": "lucasrsv-@@-taes",
      "split": {
        "dir_name": "train-rl-repos",
        "thm_dir_name": "train-rl-theorems"
      },
      "commit_hash": null,
      "compile_args": []
    },
    "path": "Basics.v",
    "theorem_start_pos": {
      "line": 1054,
      "column": 0
    },
    "theorem_end_pos": {
      "line": 1055,
      "column": 34
    },
    "proof_start_pos": {
      "line": 1056,
      "column": 0
    },
    "proof_end_pos": {
      "line": 1061,
      "column": 19
    },
    "hash": "c418596d9a77f4dc084423190048f67c07dbba1c07d96ed136e5a9c8026a3566"
  },
  {
    "project": {
      "dir_name": "lucasrsv-@@-taes",
      "split": {
        "dir_name": "train-rl-repos",
        "thm_dir_name": "train-rl-theorems"
      },
      "commit_hash": null,
      "compile_args": []
    },
    "path": "Basics.v",
    "theorem_start_pos": {
      "line": 1093,
      "column": 0
    },
    "theorem_end_pos": {
      "line": 1094,
      "column": 24
    },
    "proof_start_pos": {
      "line": 1095,
      "column": 0
    },
    "proof_end_pos": {
      "line": 1099,
      "column": 19
    },
    "hash": "c418596d9a77f4dc084423190048f67c07dbba1c07d96ed136e5a9c8026a3566"
  },
  {
    "project": {
      "dir_name": "lucasrsv-@@-taes",
      "split": {
        "dir_name": "train-rl-repos",
        "thm_dir_name": "train-rl-theorems"
      },
      "commit_hash": null,
      "compile_args": []
    },
    "path": "Basics.v",
    "theorem_start_pos": {
      "line": 1106,
      "column": 0
    },
    "theorem_end_pos": {
      "line": 1107,
      "column": 12
    },
    "proof_start_pos": {
      "line": 1108,
      "column": 0
    },
    "proof_end_pos": {
      "line": 1112,
      "column": 19
    },
    "hash": "c418596d9a77f4dc084423190048f67c07dbba1c07d96ed136e5a9c8026a3566"
  },
  {
    "project": {
      "dir_name": "lucasrsv-@@-taes",
      "split": {
        "dir_name": "train-rl-repos",
        "thm_dir_name": "train-rl-theorems"
      },
      "commit_hash": null,
      "compile_args": []
    },
    "path": "Basics.v",
    "theorem_start_pos": {
      "line": 1151,
      "column": 0
    },
    "theorem_end_pos": {
      "line": 1152,
      "column": 23
    },
    "proof_start_pos": {
      "line": 1153,
      "column": 0
    },
    "proof_end_pos": {
      "line": 1156,
      "column": 23
    },
    "hash": "c418596d9a77f4dc084423190048f67c07dbba1c07d96ed136e5a9c8026a3566"
  },
  {
    "project": {
      "dir_name": "lucasrsv-@@-taes",
      "split": {
        "dir_name": "train-rl-repos",
        "thm_dir_name": "train-rl-theorems"
      },
      "commit_hash": null,
      "compile_args": []
    },
    "path": "Basics.v",
    "theorem_start_pos": {
      "line": 1219,
      "column": 0
    },
    "theorem_end_pos": {
      "line": 1220,
      "column": 20
    },
    "proof_start_pos": {
      "line": 1221,
      "column": 0
    },
    "proof_end_pos": {
      "line": 1224,
      "column": 22
    },
    "hash": "c418596d9a77f4dc084423190048f67c07dbba1c07d96ed136e5a9c8026a3566"
  },
  {
    "project": {
      "dir_name": "lucasrsv-@@-taes",
      "split": {
        "dir_name": "train-rl-repos",
        "thm_dir_name": "train-rl-theorems"
      },
      "commit_hash": null,
      "compile_args": []
    },
    "path": "Basics.v",
    "theorem_start_pos": {
      "line": 1239,
      "column": 0
    },
    "theorem_end_pos": {
      "line": 1239,
      "column": 59
    },
    "proof_start_pos": {
      "line": 1240,
      "column": 0
    },
    "proof_end_pos": {
      "line": 1248,
      "column": 4
    },
    "hash": "c418596d9a77f4dc084423190048f67c07dbba1c07d96ed136e5a9c8026a3566"
  },
  {
    "project": {
      "dir_name": "lucasrsv-@@-taes",
      "split": {
        "dir_name": "train-rl-repos",
        "thm_dir_name": "train-rl-theorems"
      },
      "commit_hash": null,
      "compile_args": []
    },
    "path": "Basics.v",
    "theorem_start_pos": {
      "line": 1258,
      "column": 0
    },
    "theorem_end_pos": {
      "line": 1258,
      "column": 60
    },
    "proof_start_pos": {
      "line": 1259,
      "column": 0
    },
    "proof_end_pos": {
      "line": 1267,
      "column": 4
    },
    "hash": "c418596d9a77f4dc084423190048f67c07dbba1c07d96ed136e5a9c8026a3566"
  },
  {
    "project": {
      "dir_name": "lucasrsv-@@-taes",
      "split": {
        "dir_name": "train-rl-repos",
        "thm_dir_name": "train-rl-theorems"
      },
      "commit_hash": null,
      "compile_args": []
    },
    "path": "Basics.v",
    "theorem_start_pos": {
      "line": 1276,
      "column": 0
    },
    "theorem_end_pos": {
      "line": 1277,
      "column": 54
    },
    "proof_start_pos": {
      "line": 1278,
      "column": 0
    },
    "proof_end_pos": {
      "line": 1294,
      "column": 4
    },
    "hash": "c418596d9a77f4dc084423190048f67c07dbba1c07d96ed136e5a9c8026a3566"
  },
  {
    "project": {
      "dir_name": "lucasrsv-@@-taes",
      "split": {
        "dir_name": "train-rl-repos",
        "thm_dir_name": "train-rl-theorems"
      },
      "commit_hash": null,
      "compile_args": []
    },
    "path": "Basics.v",
    "theorem_start_pos": {
      "line": 1302,
      "column": 0
    },
    "theorem_end_pos": {
      "line": 1303,
      "column": 30
    },
    "proof_start_pos": {
      "line": 1304,
      "column": 0
    },
    "proof_end_pos": {
      "line": 1318,
      "column": 6
    },
    "hash": "c418596d9a77f4dc084423190048f67c07dbba1c07d96ed136e5a9c8026a3566"
  },
  {
    "project": {
      "dir_name": "lucasrsv-@@-taes",
      "split": {
        "dir_name": "train-rl-repos",
        "thm_dir_name": "train-rl-theorems"
      },
      "commit_hash": null,
      "compile_args": []
    },
    "path": "Basics.v",
    "theorem_start_pos": {
      "line": 1336,
      "column": 0
    },
    "theorem_end_pos": {
      "line": 1337,
      "column": 23
    },
    "proof_start_pos": {
      "line": 1338,
      "column": 0
    },
    "proof_end_pos": {
      "line": 1341,
      "column": 22
    },
    "hash": "c418596d9a77f4dc084423190048f67c07dbba1c07d96ed136e5a9c8026a3566"
  },
  {
    "project": {
      "dir_name": "lucasrsv-@@-taes",
      "split": {
        "dir_name": "train-rl-repos",
        "thm_dir_name": "train-rl-theorems"
      },
      "commit_hash": null,
      "compile_args": []
    },
    "path": "Basics.v",
    "theorem_start_pos": {
      "line": 1346,
      "column": 0
    },
    "theorem_end_pos": {
      "line": 1347,
      "column": 34
    },
    "proof_start_pos": {
      "line": 1348,
      "column": 0
    },
    "proof_end_pos": {
      "line": 1354,
      "column": 4
    },
    "hash": "c418596d9a77f4dc084423190048f67c07dbba1c07d96ed136e5a9c8026a3566"
  },
  {
    "project": {
      "dir_name": "lucasrsv-@@-taes",
      "split": {
        "dir_name": "train-rl-repos",
        "thm_dir_name": "train-rl-theorems"
      },
      "commit_hash": null,
      "compile_args": []
    },
    "path": "Basics.v",
    "theorem_start_pos": {
      "line": 1357,
      "column": 0
    },
    "theorem_end_pos": {
      "line": 1358,
      "column": 23
    },
    "proof_start_pos": {
      "line": 1359,
      "column": 0
    },
    "proof_end_pos": {
      "line": 1371,
      "column": 4
    },
    "hash": "c418596d9a77f4dc084423190048f67c07dbba1c07d96ed136e5a9c8026a3566"
  },
  {
    "project": {
      "dir_name": "lucasrsv-@@-taes",
      "split": {
        "dir_name": "train-rl-repos",
        "thm_dir_name": "train-rl-theorems"
      },
      "commit_hash": null,
      "compile_args": []
    },
    "path": "Basics.v",
    "theorem_start_pos": {
      "line": 1467,
      "column": 0
    },
    "theorem_end_pos": {
      "line": 1470,
      "column": 33
    },
    "proof_start_pos": {
      "line": 1471,
      "column": 0
    },
    "proof_end_pos": {
      "line": 1476,
      "column": 4
    },
    "hash": "c418596d9a77f4dc084423190048f67c07dbba1c07d96ed136e5a9c8026a3566"
  }
]